MANIFEST.in
google_base_account_view.xml
setup.py
./__init__.py
./__openerp__.py
./google_base_account.py
./wizard/__init__.py
./wizard/google_login.py
i18n/ar.po
i18n/cs.po
i18n/de.po
i18n/es.po
i18n/es_CR.po
i18n/fi.po
i18n/fr.po
i18n/google_base_account.pot
i18n/hr.po
i18n/hu.po
i18n/it.po
i18n/ja.po
i18n/mk.po
i18n/mn.po
i18n/nb.po
i18n/nl.po
i18n/pl.po
i18n/pt.po
i18n/pt_BR.po
i18n/ro.po
i18n/ru.po
i18n/sl.po
i18n/sr@latin.po
i18n/sv.po
i18n/tr.po
i18n/zh_CN.po
openerp_google_base_account.egg-info/PKG-INFO
openerp_google_base_account.egg-info/SOURCES.txt
openerp_google_base_account.egg-info/dependency_links.txt
openerp_google_base_account.egg-info/requires.txt
openerp_google_base_account.egg-info/top_level.txt
wizard/google_login_view.xml